Auto3D/.gitignore
Auto3D/SPE.py
Auto3D/__init__.py
Auto3D/auto3D.py
Auto3D/isomer_engine.py
Auto3D/ranking.py
Auto3D/tautomer.py
Auto3D/utils.py
Auto3D/utils_file.py
Auto3D/ASE/__init__.py
Auto3D/ASE/geometry.py
Auto3D/ASE/thermo.py
Auto3D/batch_opt/ANI2xt_no_rep.py
Auto3D/batch_opt/ANI2xt_rep.py
Auto3D/batch_opt/__init__.py
Auto3D/batch_opt/batchopt.py
Auto3D/models/__init__.py
Auto3D/models/aimnet2_wb97m-d3_0.jpt
Auto3D/models/aimnet2_wb97m_ens_f.jpt
Auto3D/models/ani2xt_no_repulsion.pt
AcAuto3D-1.0.1.dist-info/LICENSE
AcAuto3D-1.0.1.dist-info/METADATA
AcAuto3D-1.0.1.dist-info/WHEEL
AcAuto3D-1.0.1.dist-info/top_level.txt
AcAuto3D-1.0.1.dist-info/RECORD
